search_plot_utils/__init__.py
search_plot_utils/plotting.py
search_plot_utils/tables.py
search_plot_utils/utils.py
tests/__init__.py
tests/test_plotting.py
tests/test_tables.py
tests/test_utils.py
search_plot_utils-0.1.1.dist-info/LICENSE
search_plot_utils-0.1.1.dist-info/METADATA
search_plot_utils-0.1.1.dist-info/WHEEL
search_plot_utils-0.1.1.dist-info/top_level.txt
search_plot_utils-0.1.1.dist-info/RECORD
