Metadata-Version: 2.1
Name: search-plot-utils
Version: 0.1.1
Summary: Simplifies the visualization and analysis of search results from hyperparameter optimization.
Home-page: https://github.com/yourusername/search_plot_utils
Author: Diogo Hajjar
Author-email: diogohajjar@gmail.com
License: MIT
Classifier: Development Status :: 3 - Alpha
Classifier: Intended Audience :: Developers
Classifier: License :: OSI Approved :: MIT License
Classifier: Programming Language :: Python :: 3
Classifier: Programming Language :: Python :: 3.6
Classifier: Programming Language :: Python :: 3.7
Classifier: Programming Language :: Python :: 3.8
Classifier: Programming Language :: Python :: 3.9
Requires-Python: >=3.6
License-File: LICENSE
Requires-Dist: matplotlib
Requires-Dist: pandas
Requires-Dist: scikit-learn
